[
  {
    "number": 1,
    "title": "Strawberry, Appear!",
    "overview": "",
    "air_date": "2002-07-02",
    "still": null,
    "runtime": 25,
    "vote_average": 0,
    "tmdb_id": 791716
  },
  {
    "number": 2,
    "title": "What are the Glasses?",
    "overview": "",
    "air_date": "2002-07-09",
    "still": null,
    "runtime": 25,
    "vote_average": 0,
    "tmdb_id": 791717
  },
  {
    "number": 3,
    "title": "Get Angry, Sela!",
    "overview": "",
    "air_date": "2002-07-16",
    "still": null,
    "runtime": 25,
    "vote_average": 0,
    "tmdb_id": 791718
  },
  {
    "number": 4,
    "title": "Hard Training, and the Middle!",
    "overview": "",
    "air_date": "2002-07-23",
    "still": null,
    "runtime": 25,
    "vote_average": 0,
    "tmdb_id": 791719
  },
  {
    "number": 5,
    "title": "Yayoi Goes Straight!",
    "overview": "",
    "air_date": "2002-07-30",
    "still": null,
    "runtime": 25,
    "vote_average": 0,
    "tmdb_id": 791720
  },
  {
    "number": 6,
    "title": "Time to Train!",
    "overview": "",
    "air_date": "2002-08-06",
    "still": null,
    "runtime": 25,
    "vote_average": 0,
    "tmdb_id": 791721
  },
  {
    "number": 7,
    "title": "The Tale of Seven Men and Women",
    "overview": "",
    "air_date": "2002-08-13",
    "still": null,
    "runtime": 25,
    "vote_average": 0,
    "tmdb_id": 791722
  },
  {
    "number": 8,
    "title": "Being Called a Long-time Loser",
    "overview": "",
    "air_date": "2002-08-20",
    "still": null,
    "runtime": 25,
    "vote_average": 0,
    "tmdb_id": 791723
  },
  {
    "number": 9,
    "title": "Who Will Wear the Maid Clothes?",
    "overview": "",
    "air_date": "2002-08-27",
    "still": null,
    "runtime": 25,
    "vote_average": 0,
    "tmdb_id": 791724
  },
  {
    "number": 10,
    "title": "\"Get You\" Days",
    "overview": "",
    "air_date": "2002-09-03",
    "still": null,
    "runtime": 25,
    "vote_average": 0,
    "tmdb_id": 791725
  },
  {
    "number": 11,
    "title": "What Happened to Mako?",
    "overview": "",
    "air_date": "2002-09-10",
    "still": null,
    "runtime": 25,
    "vote_average": 0,
    "tmdb_id": 791726
  },
  {
    "number": 12,
    "title": "Dr. Sanada Doesn`t Turn Back",
    "overview": "",
    "air_date": "2002-09-17",
    "still": null,
    "runtime": 25,
    "vote_average": 0,
    "tmdb_id": 791727
  },
  {
    "number": 13,
    "title": "Full Force Strawberries",
    "overview": "",
    "air_date": "2002-10-01",
    "still": null,
    "runtime": 25,
    "vote_average": 0,
    "tmdb_id": 791728
  },
  {
    "number": 14,
    "title": "Andro White Paper",
    "overview": "",
    "air_date": "2003-03-21",
    "still": null,
    "runtime": 25,
    "vote_average": 0,
    "tmdb_id": 791729
  }
]