{
  "ids": {
    "anilist": 146316,
    "mal": 51378,
    "tmdb": 202136,
    "tmdb_type": "tv",
    "tmdb_season": null
  },
  "titles": {
    "romaji": "Senkou",
    "english": null,
    "native": "閃光",
    "synonyms": [
      "Flashlight",
      "Roselia×Eve"
    ],
    "tmdb_title": "Вспышка"
  },
  "format": "MUSIC",
  "status": "FINISHED",
  "episodes": 1,
  "duration": 2,
  "start_date": {
    "year": 2022,
    "month": 3,
    "day": 12
  },
  "end_date": {
    "year": 2022,
    "month": 3,
    "day": 12
  },
  "description": "Animated music video directed by Zemyata for the song <i>Senkou</i> by Roselia. This song is a collaboration with Eve who composed and wrote the lyrics for the track.",
  "genres": [],
  "tags": [],
  "studios": [],
  "producers": [],
  "source": "OTHER",
  "country": "JP",
  "score_anilist": 65,
  "popularity": 1052,
  "trending": 0,
  "images": {
    "poster": "https://s4.anilist.co/file/anilistcdn/media/anime/cover/large/bx146316-fSxTxFrOjjYy.png",
    "poster_color": "#d6936b",
    "banner": "https://s4.anilist.co/file/anilistcdn/media/anime/banner/146316-K9e4EtWSdmqG.jpg",
    "poster_tmdb": "https://image.tmdb.org/t/p/w780/rXhs4aC4P4Eki1UqQKpj0IM8JrL.jpg",
    "banner_tmdb": "https://image.tmdb.org/t/p/original/5bzuUQwLvUWVPMqU3Jaipyf9jc5.jpg",
    "thumbnail": "https://s4.anilist.co/file/anilistcdn/media/anime/cover/large/bx146316-fSxTxFrOjjYy.png"
  },
  "streaming": [
    {
      "site": "YouTube",
      "url": "https://www.youtube.com/watch?v=IL33TNljMz8"
    }
  ],
  "themes": [],
  "confidence": "MEDIUM",
  "match_score": 95,
  "match_signals": [
    "exact_title",
    "year_match",
    "format_match"
  ],
  "cached_at": "2026-05-05T11:59:50.887Z",
  "cache_version": 1
}