{
  "ids": {
    "anilist": 1666,
    "mal": 1666,
    "anidb": 1460,
    "tmdb": 56024,
    "tmdb_type": "tv",
    "tmdb_season": null
  },
  "titles": {
    "romaji": "Babel Nisei (1973)",
    "english": null,
    "native": "バビル２世",
    "synonyms": [
      "Babil Junior"
    ],
    "tmdb_title": "Babel II"
  },
  "format": "TV",
  "status": "FINISHED",
  "season": "WINTER",
  "season_year": 1973,
  "episodes": 39,
  "duration": 25,
  "start_date": {
    "year": 1973,
    "month": 1,
    "day": 1
  },
  "end_date": {
    "year": 1973,
    "month": 9,
    "day": 24
  },
  "description": "Life seems simple for Koichi, a young student, until he learns that he is the reincarnation of an alien protector who crashed onto the mantle of responsibility as\"defender of the Earth\", Koichi/Babel teams up with a trio of super-powered alien companions to battle the the dark forces of an evil cult leader. The war to save humanity takes Babel from the deserts of southern Asia to the upper east side of Manhattan and ultimately to a final showdown with \"the master\" in a hidden base nestled in the Swiss Alps. The action is fast-paced and deadly. The fate of the world rests in the ability of this courageous youth to tame his latent psychic power and use it to defeat the enemies of mankind.<br><br>\n(Source: AnimeNfo)",
  "genres": [
    "Adventure",
    "Mecha",
    "Sci-Fi",
    "Supernatural"
  ],
  "tags": [
    "Shounen",
    "Robots",
    "Super Power",
    "Military",
    "Conspiracy",
    "Primarily Male Cast"
  ],
  "studios": [
    "Toei Animation"
  ],
  "producers": [
    "TV Asahi"
  ],
  "source": "MANGA",
  "country": "JP",
  "score_anilist": 57,
  "popularity": 843,
  "trending": 0,
  "images": {
    "poster": "https://s4.anilist.co/file/anilistcdn/media/anime/cover/large/bx1666-vBYpqA5tAbQG.png",
    "poster_color": "#fff135",
    "banner": "https://image.tmdb.org/t/p/original/6NdwRaSDhapJbvKpBCFSxyRATxd.jpg",
    "poster_tmdb": "https://image.tmdb.org/t/p/w780/mDSi5nzj6YvyC0XykcrQfdNKbwo.jpg",
    "banner_tmdb": "https://image.tmdb.org/t/p/original/6NdwRaSDhapJbvKpBCFSxyRATxd.jpg",
    "thumbnail": "https://s4.anilist.co/file/anilistcdn/media/anime/cover/large/bx1666-vBYpqA5tAbQG.png"
  },
  "streaming": [],
  "themes": [],
  "confidence": "MEDIUM",
  "match_score": 100,
  "match_signals": [
    "year_match",
    "episode_exact",
    "format_match",
    "studio_match"
  ],
  "cached_at": "2026-05-04T04:11:27.139Z",
  "cache_version": 1
}