{
  "ids": {
    "anilist": 468,
    "mal": 468,
    "anidb": 890,
    "tmdb": 12140,
    "tmdb_type": "movie",
    "tmdb_season": null
  },
  "titles": {
    "romaji": "Innocence",
    "english": "Ghost in the Shell 2: Innocence",
    "native": "イノセンス",
    "synonyms": [
      "Ghost in the Shell - L'attacco dei cyborg"
    ],
    "tmdb_title": "Ghost in the Shell 2: Innocence"
  },
  "format": "MOVIE",
  "status": "FINISHED",
  "season": "SPRING",
  "season_year": 2004,
  "episodes": 1,
  "duration": 100,
  "start_date": {
    "year": 2004,
    "month": 3,
    "day": 6
  },
  "end_date": {
    "year": 2004,
    "month": 3,
    "day": 6
  },
  "description": "The year is 2032. With the advancement of medical technology humanity has grown into a more technologically driven creature, creating a breed of cyborg citizen. Along with the development of cybernetics the world has seen rapid development in the field of artificial intelligence, making androids a commercially viable venture.<br>\n<br>\nA recent string of murders perpetrated by a prototype female android has drawn the attention of Section 9, a unit specializing in counter cyber-terrorism. With none of the victims' families pressing charges, suspicions arise regarding the nature of the androids and their production.<br>\n<br>\nMonths have passed since the end of the Puppet Master incident, and with the Major still missing investigative duties fall to her cyborg commando partner Batou and his newly recruited biological partner, Togusa. Can the two overcome their differences and discover the truth behind this string of murders?<br>\n<br>\n(Source: Bandai Entertainment)",
  "genres": [
    "Action",
    "Psychological",
    "Sci-Fi"
  ],
  "tags": [
    "Philosophy",
    "Cyberpunk",
    "Police",
    "Artificial Intelligence",
    "CGI",
    "Male Protagonist",
    "Robots",
    "Seinen",
    "Photography",
    "Noir",
    "Cyborg",
    "Primarily Adult Cast",
    "Guns",
    "Primarily Male Cast"
  ],
  "studios": [
    "Production I.G"
  ],
  "producers": [
    "Bandai Entertainment"
  ],
  "source": "MANGA",
  "country": "JP",
  "score_anilist": 75,
  "popularity": 38659,
  "trending": 1,
  "images": {
    "poster": "https://s4.anilist.co/file/anilistcdn/media/anime/cover/large/nx468-rfiX1uY8bsPp.jpg",
    "banner": "https://s4.anilist.co/file/anilistcdn/media/anime/banner/468-V8L7r2QZaNeS.jpg",
    "poster_tmdb": "https://image.tmdb.org/t/p/w780/aBfO6rxsIQ0dpvk2pUhFVlb2fZt.jpg",
    "banner_tmdb": "https://image.tmdb.org/t/p/original/8Cbzx17QdJ6xBx2uDkdlpWsemGg.jpg",
    "thumbnail": "https://s4.anilist.co/file/anilistcdn/media/anime/cover/large/nx468-rfiX1uY8bsPp.jpg"
  },
  "streaming": [],
  "themes": [],
  "confidence": "HIGH",
  "match_score": 130,
  "match_signals": [
    "exact_title",
    "year_match",
    "format_match",
    "studio_match"
  ],
  "cached_at": "2026-05-03T05:41:30.141Z",
  "cache_version": 1
}