{
  "ids": {
    "anilist": 2070,
    "mal": 2070,
    "tmdb": 132874,
    "tmdb_type": "tv",
    "tmdb_season": null
  },
  "titles": {
    "romaji": "Guy",
    "english": "Guy: Double Target",
    "native": "ガイ",
    "synonyms": [
      "Guy: Awakening of the Devil",
      "Guy: Second Target",
      "ガイ -  妖魔覚醒",
      "Guy: Youma Kakusei",
      "Guy -Youma Awakening-"
    ],
    "tmdb_title": "Guy Double Target"
  },
  "format": "OVA",
  "status": "FINISHED",
  "season": "WINTER",
  "season_year": 1988,
  "episodes": 2,
  "duration": 34,
  "start_date": {
    "year": 1988,
    "month": 12,
    "day": 6
  },
  "end_date": {
    "year": 1992,
    "month": 7,
    "day": 15
  },
  "description": "Guy is just one of those misunderstood, lovable fellows who just happens to be one of the nastiest soldiers of fortune you've ever seen... and his partner is worse! They could be, however, the only thing that can battle Dr. Vail and breathe afterwards!<br><br>\n(Source: AniDB)",
  "genres": [
    "Action",
    "Hentai",
    "Sci-Fi"
  ],
  "tags": [
    "Body Horror",
    "Gore",
    "Male Protagonist",
    "Rape"
  ],
  "studios": [
    "Friends",
    "AIC"
  ],
  "producers": [],
  "source": "ORIGINAL",
  "country": "JP",
  "score_anilist": 50,
  "popularity": 833,
  "trending": 0,
  "images": {
    "poster": "https://s4.anilist.co/file/anilistcdn/media/anime/cover/large/bx2070-Zmk0e2kGV3V5.jpg",
    "poster_color": "#e44328",
    "poster_tmdb": "https://image.tmdb.org/t/p/w780/l11spnhIQTg8HhX9GdPXyRxJffg.jpg",
    "thumbnail": "https://s4.anilist.co/file/anilistcdn/media/anime/cover/large/bx2070-Zmk0e2kGV3V5.jpg"
  },
  "streaming": [],
  "themes": [],
  "confidence": "HIGH",
  "match_score": 135,
  "match_signals": [
    "exact_title",
    "year_match",
    "episode_exact",
    "format_match"
  ],
  "cached_at": "2026-05-05T04:52:42.911Z",
  "cache_version": 1
}