{
  "ids": {
    "anilist": 110464,
    "mal": 40111,
    "anidb": 15250,
    "tmdb": 615453,
    "tmdb_type": "movie",
    "tmdb_season": null
  },
  "titles": {
    "romaji": "Nezha: Zhi Mo Tong Jiang Shi",
    "english": "Ne Zha",
    "native": "哪吒之魔童降世",
    "synonyms": [
      "Nezha Zhi Motong Jiangshi",
      "Nezha: The Devil's Birth",
      "Nézhā zhī Mótóng Jiàngshì"
    ],
    "tmdb_title": "Ne Zha"
  },
  "format": "MOVIE",
  "status": "FINISHED",
  "episodes": 1,
  "duration": 110,
  "start_date": {
    "year": 2019,
    "month": 7,
    "day": 26
  },
  "end_date": {
    "year": 2019,
    "month": 7,
    "day": 26
  },
  "description": "A young boy, Nezha, is birthed from a heavenly pearl by the Primeval Lord of Heaven. Born with unique powers, Nezha finds himself as an outcast who is hated and feared. Destined by prophecy to bring destruction to the world, the young boy must choose between good and evil in order to break the shackles of fate and become the hero.\n<br><br>\n(Source: Well Go USA Entertainment)",
  "genres": [
    "Action",
    "Comedy",
    "Drama",
    "Fantasy"
  ],
  "tags": [
    "Mythology",
    "Full CGI",
    "Male Protagonist",
    "Demons",
    "Gods",
    "Classic Literature",
    "Magic",
    "Dragons",
    "Historical"
  ],
  "studios": [
    "Coco Cartoon"
  ],
  "producers": [],
  "source": "OTHER",
  "country": "CN",
  "score_anilist": 75,
  "popularity": 7306,
  "trending": 1,
  "images": {
    "poster": "https://s4.anilist.co/file/anilistcdn/media/anime/cover/large/bx110464-gU0stanOBGIs.png",
    "poster_color": "#f1c935",
    "banner": "https://s4.anilist.co/file/anilistcdn/media/anime/banner/110464-3EGEE4la8dbe.jpg",
    "poster_tmdb": "https://image.tmdb.org/t/p/w780/phM9bb6s9c60LA8qwsdk7U1N2cS.jpg",
    "banner_tmdb": "https://image.tmdb.org/t/p/original/k1pJslKr4aDayw9kWwWnlC3MIP3.jpg",
    "thumbnail": "https://s4.anilist.co/file/anilistcdn/media/anime/cover/large/bx110464-gU0stanOBGIs.png"
  },
  "streaming": [
    {
      "site": "Tencent Video",
      "url": "https://v.qq.com/detail/t/zr5a67l333ehzu9.html"
    },
    {
      "site": "Netflix",
      "url": "https://www.netflix.com/title/81191389"
    }
  ],
  "themes": [],
  "confidence": "MEDIUM",
  "match_score": 105,
  "match_signals": [
    "exact_title",
    "year_match",
    "format_match"
  ],
  "cached_at": "2026-05-04T18:12:35.109Z",
  "cache_version": 1
}