{
  "ids": {
    "anilist": 194389,
    "mal": 62005,
    "anidb": 19637,
    "tmdb": 296933,
    "tmdb_type": "tv",
    "tmdb_season": null
  },
  "titles": {
    "romaji": "Koala Enikki",
    "english": "Koala's Diary",
    "native": "コアラ絵日記",
    "synonyms": [
      "Koala's Diary",
      "บันทึกไดอารีของโคอาล่า"
    ],
    "tmdb_title": "Koala's Diary"
  },
  "format": "ONA",
  "status": "RELEASING",
  "season": "FALL",
  "season_year": 2025,
  "episodes": 39,
  "duration": 2,
  "start_date": {
    "year": 2025,
    "month": 10,
    "day": 2
  },
  "end_date": {
    "year": null,
    "month": null,
    "day": null
  },
  "next_airing": {
    "episode": 33,
    "at": "2026-05-21T18:00:00.000Z"
  },
  "description": "The manga is about Koala who writes about daily life, whether it's good or bad, happy or sad, Koala treats every day as a precious day. Koala believes that today is a good day, and tomorrow will be a good day too.\n<br><br>\n(Source: Anime News Network)",
  "genres": [
    "Slice of Life"
  ],
  "tags": [
    "Anthropomorphism",
    "Primarily Animal Cast",
    "No Dialogue",
    "Iyashikei",
    "Episodic",
    "Animals"
  ],
  "studios": [
    "studio MOTHER"
  ],
  "producers": [
    "KADOKAWA"
  ],
  "source": "MANGA",
  "country": "JP",
  "score_anilist": 50,
  "popularity": 444,
  "trending": 0,
  "images": {
    "poster": "https://s4.anilist.co/file/anilistcdn/media/anime/cover/large/bx194389-DAbj4TOj5GB9.png",
    "poster_color": "#e47843",
    "banner": "https://image.tmdb.org/t/p/original/5y0kfKx3X5SlmtJD26YI1oUsBpZ.jpg",
    "poster_tmdb": "https://image.tmdb.org/t/p/w780/5IwLOuBjc9JhkJbkcyMft7OfKJK.jpg",
    "banner_tmdb": "https://image.tmdb.org/t/p/original/5y0kfKx3X5SlmtJD26YI1oUsBpZ.jpg",
    "thumbnail": "https://s4.anilist.co/file/anilistcdn/media/anime/cover/large/bx194389-DAbj4TOj5GB9.png"
  },
  "streaming": [
    {
      "site": "YouTube",
      "url": "https://www.youtube.com/channel/UCPTx35gchBwV2DL6Gf83AnQ"
    },
    {
      "site": "YouTube",
      "url": "https://www.youtube.com/playlist?list=PLxSscENEp7Jg8-ovZUfZSZYidXFSwIpA9"
    },
    {
      "site": "Ani-One Asia",
      "url": "https://www.youtube.com/channel/UC0wNSTMWIL3qaorLx0jie6A"
    },
    {
      "site": "CatchPlay",
      "url": "https://www.catchplay.com/"
    }
  ],
  "themes": [],
  "confidence": "HIGH",
  "match_score": 130,
  "match_signals": [
    "exact_title",
    "year_match",
    "format_match",
    "studio_match"
  ],
  "cached_at": "2026-05-18T18:36:46.321Z",
  "cache_version": 1,
  "score_mal": 6.35
}