{
  "ids": {
    "anilist": 160,
    "mal": 160,
    "anidb": 114,
    "tmdb": 26340,
    "tmdb_type": "tv",
    "tmdb_season": null
  },
  "titles": {
    "romaji": "Ima, Soko ni Iru Boku",
    "english": "Now and Then, Here and There",
    "native": "今、そこにいる僕",
    "synonyms": [
      "L'Autre Monde",
      "الآن ، وبعد ذلك ، هنا وهناك",
      "此时此刻的我",
      "超時空幻境"
    ],
    "tmdb_title": "Now and Then, Here and There"
  },
  "format": "TV",
  "status": "FINISHED",
  "season": "FALL",
  "season_year": 1999,
  "episodes": 13,
  "duration": 25,
  "start_date": {
    "year": 1999,
    "month": 10,
    "day": 14
  },
  "end_date": {
    "year": 2000,
    "month": 1,
    "day": 20
  },
  "description": "Shu is a typical Japanese boy, but has an unbeatable, optimistic and determined attitude. However, when he sees a mysterious girl with strange eyes named Lala-Ru up on a smokestack, he is soon pulled into a strange desert world. Shu soon discovers the true terrors of war, which includes genocide, brutal torture, hunger, thirst, and child exploitation. Now Shu is trying to save Lala-Ru, as well as his hard earned, and often relunctant, new friends from the insane dictator, Hamdo. Whether Shu can possibly accomplish saving those he cares about while still holding up to his values remains to be seen. <br><br>\n(Source: Anime News Network) ",
  "genres": [
    "Adventure",
    "Drama",
    "Fantasy",
    "Sci-Fi"
  ],
  "tags": [
    "Tragedy",
    "Dystopian",
    "War",
    "Survival",
    "Primarily Child Cast",
    "Post-Apocalyptic",
    "Coming of Age",
    "Isekai",
    "Military",
    "Desert",
    "Philosophy",
    "Guns",
    "Male Protagonist",
    "Orphan",
    "Torture"
  ],
  "studios": [
    "AIC"
  ],
  "producers": [
    "Pioneer LDC",
    "Central Park Media"
  ],
  "source": "ORIGINAL",
  "country": "JP",
  "score_anilist": 73,
  "popularity": 41466,
  "trending": 3,
  "images": {
    "poster": "https://s4.anilist.co/file/anilistcdn/media/anime/cover/large/bx160-t5rKPAhZoznO.jpg",
    "poster_color": "#f18635",
    "banner": "https://s4.anilist.co/file/anilistcdn/media/anime/banner/160-LbiEyoQyuDaL.jpg",
    "poster_tmdb": "https://image.tmdb.org/t/p/w780/vjw3X2Tv1C9zT2StFTdgPEJkxnB.jpg",
    "banner_tmdb": "https://image.tmdb.org/t/p/original/8HFbFeUdDFJRn6BwibLPvM8awsm.jpg",
    "thumbnail": "https://s4.anilist.co/file/anilistcdn/media/anime/cover/large/bx160-t5rKPAhZoznO.jpg"
  },
  "streaming": [],
  "themes": [],
  "confidence": "HIGH",
  "match_score": 135,
  "match_signals": [
    "exact_title",
    "year_match",
    "episode_exact",
    "format_match"
  ],
  "cached_at": "2026-05-03T05:33:26.440Z",
  "cache_version": 1
}