[
  {
    "number": 1,
    "title": "Rejuvenate your youth and restart your life",
    "overview": "",
    "air_date": "2024-05-23",
    "still": "https://image.tmdb.org/t/p/w500/eNpJE7rV9MF0b4L8WINJfdGPMjg.jpg",
    "runtime": 17,
    "vote_average": 8,
    "tmdb_id": 5247959
  },
  {
    "number": 2,
    "title": "New exam questions",
    "overview": "",
    "air_date": "2024-05-23",
    "still": "https://image.tmdb.org/t/p/w500/ajW9D4HqMnSZk5Lt0POUjLM7RIL.jpg",
    "runtime": 17,
    "vote_average": 8,
    "tmdb_id": 5247962
  },
  {
    "number": 3,
    "title": "Freshmen are \"afraid\" that starting college will go too smoothly",
    "overview": "",
    "air_date": "2024-05-30",
    "still": "https://image.tmdb.org/t/p/w500/hIOBq06rSxuirPPglDPFzfWd5dG.jpg",
    "runtime": 18,
    "vote_average": 8,
    "tmdb_id": 5247963
  },
  {
    "number": 4,
    "title": "Wei Chengjun",
    "overview": "",
    "air_date": "2024-06-06",
    "still": "https://image.tmdb.org/t/p/w500/3AYLossMJdGCdOXx7MDCkT3OcuP.jpg",
    "runtime": 18,
    "vote_average": 8,
    "tmdb_id": 5247964
  },
  {
    "number": 5,
    "title": "\"Curse\"",
    "overview": "",
    "air_date": "2024-06-13",
    "still": "https://image.tmdb.org/t/p/w500/4yIWibf4Ur7UPMyF2wN7rhuLlhh.jpg",
    "runtime": 17,
    "vote_average": 8,
    "tmdb_id": 5247965
  },
  {
    "number": 6,
    "title": "Dong Cuican! You scumbag!",
    "overview": "",
    "air_date": "2024-06-20",
    "still": "https://image.tmdb.org/t/p/w500/qS5YKtUnilw9FOMpcthQnUEMGJK.jpg",
    "runtime": 18,
    "vote_average": 8,
    "tmdb_id": 5247966
  },
  {
    "number": 7,
    "title": "Finished……",
    "overview": "",
    "air_date": "2024-06-27",
    "still": "https://image.tmdb.org/t/p/w500/lmxL12Tg82x4GmtXlQ614T3VkuG.jpg",
    "runtime": 16,
    "vote_average": 8,
    "tmdb_id": 5247967
  },
  {
    "number": 8,
    "title": "Yan Jinyu requests to join the battle!",
    "overview": "",
    "air_date": "2024-07-04",
    "still": "https://image.tmdb.org/t/p/w500/bGt6IoXhSrEmuveyVU9MmGjDUdD.jpg",
    "runtime": 17,
    "vote_average": 8,
    "tmdb_id": 5247968
  },
  {
    "number": 9,
    "title": "To make known to the public",
    "overview": "",
    "air_date": "2024-07-11",
    "still": "https://image.tmdb.org/t/p/w500/fit3h4QzHXDwra9uN2MAK6cNspU.jpg",
    "runtime": 16,
    "vote_average": 0,
    "tmdb_id": 5469771
  },
  {
    "number": 10,
    "title": "After Becoming Famous",
    "overview": "",
    "air_date": "2024-07-18",
    "still": "https://image.tmdb.org/t/p/w500/v2DNZgCFihtWFR3w5cuWtsP7a99.jpg",
    "runtime": 18,
    "vote_average": 0,
    "tmdb_id": 5469772
  },
  {
    "number": 11,
    "title": "Returning to the Original Intention",
    "overview": "",
    "air_date": "2024-07-25",
    "still": "https://image.tmdb.org/t/p/w500/miuYhZy4Ws782KDc6vgzyJEQo4n.jpg",
    "runtime": 17,
    "vote_average": 0,
    "tmdb_id": 5469773
  },
  {
    "number": 12,
    "title": "I’m Your Father!",
    "overview": "",
    "air_date": "2024-08-01",
    "still": "https://image.tmdb.org/t/p/w500/mrLhdDasAZoz3FBdlyJftOzpyjx.jpg",
    "runtime": 18,
    "vote_average": 0,
    "tmdb_id": 5469774
  },
  {
    "number": 13,
    "title": "One Million",
    "overview": "",
    "air_date": "2024-08-08",
    "still": "https://image.tmdb.org/t/p/w500/2sF4vwATac4op5ID0BSq6Wt4ZY7.jpg",
    "runtime": 18,
    "vote_average": 0,
    "tmdb_id": 5469775
  },
  {
    "number": 14,
    "title": "Farewell: Countdown",
    "overview": "",
    "air_date": "2024-08-15",
    "still": "https://image.tmdb.org/t/p/w500/bYUv1834MojGAHiFwEyV7uOLsr7.jpg",
    "runtime": 18,
    "vote_average": 0,
    "tmdb_id": 5469776
  },
  {
    "number": 15,
    "title": "Farewell: Bucket List",
    "overview": "",
    "air_date": "2024-08-22",
    "still": "https://image.tmdb.org/t/p/w500/8AM6MJ0ercFIDByNzEgY79XBsLE.jpg",
    "runtime": 17,
    "vote_average": 0,
    "tmdb_id": 5469777
  },
  {
    "number": 16,
    "title": "Farewell: A Surprise",
    "overview": "",
    "air_date": "2024-08-29",
    "still": "https://image.tmdb.org/t/p/w500/tlhQ1b6Bsz4qusvVw2sUSN03jgP.jpg",
    "runtime": 17,
    "vote_average": 0,
    "tmdb_id": 5469778
  },
  {
    "number": 17,
    "title": "Farewell: Burning Myself Out",
    "overview": "",
    "air_date": "2024-09-05",
    "still": "https://image.tmdb.org/t/p/w500/vi241KO4INeFBTaDoFKzyaVpTi.jpg",
    "runtime": 17,
    "vote_average": 0,
    "tmdb_id": 5469779
  },
  {
    "number": 18,
    "title": "Farewell: Account Deactivated",
    "overview": "",
    "air_date": "2024-09-12",
    "still": "https://image.tmdb.org/t/p/w500/5G0A4JjB64cxiFJXbMhV1BlYcCM.jpg",
    "runtime": 18,
    "vote_average": 0,
    "tmdb_id": 5469780
  }
]