{
  "ids": {
    "anilist": 104360,
    "mal": 28067,
    "anidb": 6908,
    "tmdb": 742339,
    "tmdb_type": "movie",
    "tmdb_season": null
  },
  "titles": {
    "romaji": "Kyouryoku Boukuusen",
    "english": null,
    "native": "協力防空戦",
    "synonyms": [],
    "tmdb_title": "Kyouryoku Boukuusen"
  },
  "format": "MOVIE",
  "status": "FINISHED",
  "episodes": 1,
  "duration": 10,
  "start_date": {
    "year": 1942,
    "month": null,
    "day": null
  },
  "end_date": {
    "year": 1942,
    "month": null,
    "day": null
  },
  "description": "A wartime propaganda animation which is somewhat educational. It depicts American bombings in Japan and reminds people to get to shelters. Another portion portrays Japanese planes shooting down incoming American aircraft during an air raid. The anime also encourages citizens to pitch in and put out fires caused by falling bombs.\n<br><br>\n(Source: simkl)",
  "genres": [
    "Action"
  ],
  "tags": [
    "War",
    "Achromatic",
    "Animals"
  ],
  "studios": [],
  "producers": [],
  "source": "ORIGINAL",
  "country": "JP",
  "score_anilist": 40,
  "popularity": 314,
  "trending": 0,
  "images": {
    "poster": "https://s4.anilist.co/file/anilistcdn/media/anime/cover/medium/104360-yURPo0vwNYTn.jpg",
    "poster_tmdb": "https://image.tmdb.org/t/p/w780/oF54sBcfWu479wZlsSEGcRqmPWt.jpg",
    "thumbnail": "https://s4.anilist.co/file/anilistcdn/media/anime/cover/medium/104360-yURPo0vwNYTn.jpg"
  },
  "streaming": [],
  "themes": [],
  "confidence": "MEDIUM",
  "match_score": 105,
  "match_signals": [
    "exact_title",
    "year_match",
    "format_match"
  ],
  "cached_at": "2026-05-04T15:32:59.072Z",
  "cache_version": 1
}